mcshell/Matrix3.py
mcshell/Vec3.py
mcshell/__init__.py
mcshell/blueprints/control_api.py
mcshell/blueprints/ipython_api.py
mcshell/blueprints/powers_api.py
mcshell/constants.py
mcshell/data/FruitJuice-0.3.0.jar
mcshell/data/FruitJuice-0.4.0.jar
mcshell/data/FruitJuice-0.4.1.jar
mcshell/data/app/control.a8439284.css
mcshell/data/app/control.a8439284.css.map
mcshell/data/app/control.b03e9afc.js
mcshell/data/app/control.b03e9afc.js.map
mcshell/data/app/control.html
mcshell/data/app/index.html
mcshell/data/app/mced.9b908af4.css
mcshell/data/app/mced.9b908af4.css.map
mcshell/data/app/mced.a4de160c.js
mcshell/data/app/mced.a4de160c.js.map
mcshell/data/app/mced.b6ed8b22.css
mcshell/data/app/mced.b6ed8b22.css.map
mcshell/data/app/mced.d19475c4.js
mcshell/data/app/mced.d19475c4.js.map
mcshell/data/app/toolbox.f17a15a5.xml
mcshell/data/control_layout.json
mcshell/data/doc/command_docs.pkl
mcshell/data/entities/entity_id_map.pkl
mcshell/data/entities/generate_entity_blocks.mjs
mcshell/data/entities/pickers.json
mcshell/data/materials/colourables.json
mcshell/data/materials/generate_material_blocks.mjs
mcshell/data/materials/materials.pkl
mcshell/data/materials/mcblocks.csv
mcshell/data/materials/pickers.json
mcshell/data/materials/singles.json
mcshell/data/paper-global-template.yaml
mcshell/data/powers/stdlib.json
mcshell/data/toolbox_template.xml
mcshell/data/webpage-cache/%3F.pkl
mcshell/data/webpage-cache/Commands.pkl
mcshell/data/webpage-cache/EntityType.java.pkl
mcshell/data/webpage-cache/Material.html.pkl
mcshell/data/webpage-cache/ability.pkl
mcshell/data/webpage-cache/advancement.pkl
mcshell/data/webpage-cache/alwaysday.pkl
mcshell/data/webpage-cache/attribute.pkl
mcshell/data/webpage-cache/ban-ip.pkl
mcshell/data/webpage-cache/ban.pkl
mcshell/data/webpage-cache/banlist.pkl
mcshell/data/webpage-cache/bossbar.pkl
mcshell/data/webpage-cache/camera.pkl
mcshell/data/webpage-cache/camerashake.pkl
mcshell/data/webpage-cache/changesetting.pkl
mc_shell-0.6.7.dist-info/METADATA
mc_shell-0.6.7.dist-info/WHEEL
mc_shell-0.6.7.dist-info/entry_points.txt
mc_shell-0.6.7.dist-info/licenses/LICENSE
mc_shell-0.6.7.dist-info/RECORD
