Metadata-Version: 2.4
Name: mc-shell
Version: 0.6.7
Summary: An interactive shell and editor for controlling Minecraft servers and creating powers.
License-File: LICENSE
Author: Jeff
Author-email: jeff@thinkae.org
Requires-Python: >=3.9,<4.0
Classifier: Programming Language :: Python :: 3
Classifier: Programming Language :: Python :: 3.9
Classifier: Programming Language :: Python :: 3.10
Classifier: Programming Language :: Python :: 3.11
Classifier: Programming Language :: Python :: 3.12
Classifier: Programming Language :: Python :: 3.13
Classifier: Programming Language :: Python :: 3.14
Requires-Dist: aio-mc-rcon
Requires-Dist: beautifulsoup4
Requires-Dist: blockapily
Requires-Dist: click
Requires-Dist: eventlet (>=0.40.2,<0.41.0)
Requires-Dist: flask
Requires-Dist: flask-cors
Requires-Dist: flask-socketio
Requires-Dist: ipython
Requires-Dist: numpy
Requires-Dist: pexpect
Requires-Dist: pickleshare
Requires-Dist: python-socketio[client]
Requires-Dist: pyyaml (>=6.0.2,<7.0.0)
Requires-Dist: rcon
Requires-Dist: requests
Requires-Dist: rich
Requires-Dist: voxelmap (>=5.1.1,<6.0.0)
Requires-Dist: yarl (==1.20.1)
